aurora/Aurora.py
aurora/CLI.py
aurora/Controller.py
aurora/Forms.py
aurora/Model.py
aurora/SQL.py
aurora/Template.py
aurora/__init__.py
aurora/connector.py
aurora/helpers.py
aurora/init.py
aurora/security.py
aurora/blueprints/__init__.py
aurora/blueprints/controller.zip
aurora/blueprints/controllers.zip
aurora/blueprints/form.zip
aurora/blueprints/forms.zip
aurora/blueprints/init.zip
aurora/blueprints/model.zip
aurora/blueprints/model_safe.zip
aurora/blueprints/statics.zip
aurora/blueprints/users_model.zip
aurora/blueprints/users_model_safe.zip
aurora/blueprints/view.zip
aurora/blueprints/views.zip
aurora_mvc-0.9.7.dist-info/licenses/LICENSE
aurora_mvc-0.9.7.dist-info/METADATA
aurora_mvc-0.9.7.dist-info/WHEEL
aurora_mvc-0.9.7.dist-info/top_level.txt
aurora_mvc-0.9.7.dist-info/RECORD
