Metadata-Version: 2.4
Name: aurora-mvc
Version: 0.9.7
Summary: Aurora is an MVC web framework for creating RESTFUL CRUD applications quickly and simply
Home-page: https://github.com/heminsatya/aurora
Author: Hemin Satya
Author-email: heminsatya@gmail.com
License: MIT
Project-URL: source, https://github.com/heminsatya/aurora
Project-URL: Documentation, https://github.com/heminsatya/aurora/tree/main/docs
Project-URL: Changelog, https://github.com/heminsatya/aurora/tree/main/changes
Project-URL: Issues, https://github.com/heminsatya/aurora/issues
Keywords: aurora,mvc,web,framework
Classifier: Programming Language :: Python :: 3
Classifier: Programming Language :: Python :: 3.6
Classifier: Programming Language :: Python :: 3.7
Classifier: Programming Language :: Python :: 3.8
Classifier: Programming Language :: Python :: 3.9
Classifier: Programming Language :: Python :: 3.10
Classifier: License :: OSI Approved :: MIT License
Classifier: Operating System :: OS Independent
Requires-Python: >=3.6
License-File: LICENSE
Dynamic: license-file
